pre_commit_snippet/__init__.py
pre_commit_snippet/cache.py
pre_commit_snippet/cli.py
pre_commit_snippet/config.py
pre_commit_snippet/git.py
pre_commit_snippet/logging.py
pre_commit_snippet/snippet.py
pre_commit_snippets-2.0.0.dist-info/METADATA
pre_commit_snippets-2.0.0.dist-info/WHEEL
pre_commit_snippets-2.0.0.dist-info/entry_points.txt
pre_commit_snippets-2.0.0.dist-info/top_level.txt
pre_commit_snippets-2.0.0.dist-info/RECORD
