Metadata-Version: 2.4
Name: pre-commit-snippets
Version: 2.0.0
Summary: Pre-commit hook that syncs markdown snippets from a central repository
License-Expression: MIT
Project-URL: Homepage, https://github.com/RemoteRabbit/pre-commit-snippets
Project-URL: Documentation, https://remoterabbit.github.io/pre-commit-snippets
Project-URL: Repository, https://github.com/RemoteRabbit/pre-commit-snippets
Project-URL: Issues, https://github.com/RemoteRabbit/pre-commit-snippets/issues
Keywords: pre-commit,snippets,markdown,documentation,sync
Classifier: Development Status :: 4 - Beta
Classifier: Environment :: Console
Classifier: Intended Audience :: Developers
Classifier: Operating System :: OS Independent
Classifier: Programming Language :: Python :: 3
Classifier: Programming Language :: Python :: 3.9
Classifier: Programming Language :: Python :: 3.10
Classifier: Programming Language :: Python :: 3.11
Classifier: Programming Language :: Python :: 3.12
Classifier: Programming Language :: Python :: 3.13
Classifier: Topic :: Software Development :: Documentation
Classifier: Topic :: Software Development :: Pre-processors
Requires-Python: >=3.9
Provides-Extra: docs
Requires-Dist: mkdocs-material[imaging]>=9.5; extra == "docs"
Requires-Dist: mkdocstrings[python]>=0.24; extra == "docs"
Requires-Dist: mkdocs-git-revision-date-localized-plugin>=1.2; extra == "docs"
Requires-Dist: mkdocs-git-committers-plugin-2>=2.2; extra == "docs"
Requires-Dist: mkdocs-minify-plugin>=0.8; extra == "docs"
Requires-Dist: mkdocs-macros-plugin>=1.0; extra == "docs"
Requires-Dist: mkdocs-redirects>=1.2; extra == "docs"
Requires-Dist: mike>=2.0; extra == "docs"
Requires-Dist: pillow>=10.0; extra == "docs"
Requires-Dist: cairosvg>=2.7; extra == "docs"
